setup.py
codey/__init__.py
codey-0.0.1.dist-info/METADATA
codey-0.0.1.dist-info/WHEEL
codey-0.0.1.dist-info/top_level.txt
codey-0.0.1.dist-info/RECORD
