Metadata-Version: 2.1
Name: codey
Version: 0.0.1
Summary: library for codey
Home-page: https://makeblock.com
Author: makeblock
Author-email: flashindream@gmail.com
License: UNKNOWN
Platform: UNKNOWN
Requires-Dist: makeblock
